nsidc/iceflow/__init__.py
nsidc/iceflow/api.py
nsidc/iceflow/py.typed
nsidc/iceflow/data/__init__.py
nsidc/iceflow/data/atm1b.py
nsidc/iceflow/data/fetch.py
nsidc/iceflow/data/glah06.py
nsidc/iceflow/data/ilvis2.py
nsidc/iceflow/data/models.py
nsidc/iceflow/data/read.py
nsidc/iceflow/data/supported_datasets.py
nsidc/iceflow/itrf/__init__.py
nsidc/iceflow/itrf/converter.py
nsidc/iceflow/itrf/plate_boundaries.py
nsidc_iceflow-1.1.0.dist-info/METADATA
nsidc_iceflow-1.1.0.dist-info/WHEEL
nsidc_iceflow-1.1.0.dist-info/licenses/LICENSE
nsidc_iceflow-1.1.0.dist-info/RECORD
