Metadata-Version: 2.4
Name: nsidc-iceflow
Version: 1.1.0
Summary: Harmonized access to (pre)OIB/IceSAT/IceSAT2 data
Project-URL: Homepage, https://github.com/NSIDC/nsidc-iceflow
Project-URL: Bug Tracker, https://github.com/NSIDC/nsidc-iceflow/issues
Project-URL: Discussions, https://github.com/NSIDC/nsidc-iceflow/discussions
Project-URL: Changelog, https://github.com/NSIDC/nsidc-iceflow/releases
Author-email: NSIDC <nsidc@nsidc.org>
License: This software was developed by the National Snow and Ice Data Center (NSIDC) at
License-File: LICENSE
Classifier: Development Status :: 1 - Planning
Classifier: Intended Audience :: Developers
Classifier: Intended Audience :: Science/Research
Classifier: License :: OSI Approved :: MIT License
Classifier: Operating System :: OS Independent
Classifier: Programming Language :: Python
Classifier: Programming Language :: Python :: 3
Classifier: Programming Language :: Python :: 3 :: Only
Classifier: Programming Language :: Python :: 3.11
Classifier: Programming Language :: Python :: 3.12
Classifier: Topic :: Scientific/Engineering
Classifier: Typing :: Typed
Requires-Python: >=3.11
Requires-Dist: dask[dataframe]>=2024.10.0
Requires-Dist: earthaccess>=0.10.0
Requires-Dist: gps-timemachine>=1.1.4
Requires-Dist: h5py>=3.11
Requires-Dist: loguru>=0.7.2
Requires-Dist: numpy>=2.0.1
Requires-Dist: pandas>=2.2
Requires-Dist: pandera[mypy]~=0.23.0
Requires-Dist: pydantic>=2.8.2
Requires-Dist: pyproj>=3.6.1
Requires-Dist: pyyaml>=6.0.2
Requires-Dist: shapely>=2.0.5
Provides-Extra: dev
Requires-Dist: bump-my-version; extra == 'dev'
Requires-Dist: invoke; extra == 'dev'
Requires-Dist: mypy>=1.16.0; extra == 'dev'
Requires-Dist: pandas-stubs>=2.2; extra == 'dev'
Requires-Dist: pre-commit; extra == 'dev'
Requires-Dist: pytest; extra == 'dev'
Provides-Extra: docs
Requires-Dist: furo>=2023.08.17; extra == 'docs'
Requires-Dist: myst-nb; extra == 'docs'
Requires-Dist: myst-parser>=0.13; extra == 'docs'
Requires-Dist: sphinx-autobuild; extra == 'docs'
Requires-Dist: sphinx-autodoc-typehints; extra == 'docs'
Requires-Dist: sphinx-copybutton; extra == 'docs'
Requires-Dist: sphinx>=7.0; extra == 'docs'
Provides-Extra: notebooks
Requires-Dist: icepyx>=2.0.0; extra == 'notebooks'
Requires-Dist: ipympl; extra == 'notebooks'
Requires-Dist: jupyterlab; extra == 'notebooks'
Requires-Dist: matplotlib; extra == 'notebooks'
